invenio_pure/__init__.py
invenio_pure/cli.py
invenio_pure/config.py
invenio_pure/errors.py
invenio_pure/ext.py
invenio_pure/jobs.py
invenio_pure/proxies.py
invenio_pure/tasks.py
invenio_pure/types.py
invenio_pure/records/__init__.py
invenio_pure/records/api.py
invenio_pure/records/config.py
invenio_pure/records/models.py
invenio_pure/services/__init__.py
invenio_pure/services/config.py
invenio_pure/services/decorators.py
invenio_pure/services/services.py
invenio_pure-1.4.0.dist-info/licenses/AUTHORS.rst
invenio_pure-1.4.0.dist-info/licenses/LICENSE
invenio_pure-1.4.0.dist-info/METADATA
invenio_pure-1.4.0.dist-info/WHEEL
invenio_pure-1.4.0.dist-info/entry_points.txt
invenio_pure-1.4.0.dist-info/top_level.txt
invenio_pure-1.4.0.dist-info/RECORD
