Metadata-Version: 2.4
Name: invenio-pure
Version: 1.4.0
Summary: "Provides API for PURE."
Home-page: https://github.com/tu-graz-library/invenio-pure
Author: Graz University of Technology.
Author-email: info@inveniosoftware.org
License: MIT
Platform: any
Classifier: Development Status :: 5 - Production/Stable
Classifier: Programming Language :: Python :: 3.12
Classifier: Programming Language :: Python :: 3.13
Requires-Python: >=3.12
License-File: LICENSE
License-File: AUTHORS.rst
Requires-Dist: click>=7.0.0
Requires-Dist: click-params>=0.4.0
Requires-Dist: invenio-access>=2.0.0
Requires-Dist: invenio-accounts>=3.0.0
Requires-Dist: invenio-celery>=1.2.5
Requires-Dist: invenio-jobs>=3.0.0
Requires-Dist: requests>=2.0.0
Provides-Extra: tests
Requires-Dist: pytest-black-ng>=0.4.0; extra == "tests"
Requires-Dist: pytest-invenio>=1.4.3; extra == "tests"
Requires-Dist: invenio-search[opensearch2]>=2.1.0; extra == "tests"
Requires-Dist: ruff>=0.5.4; extra == "tests"
Requires-Dist: Sphinx>=4.5; extra == "tests"
Dynamic: license-file
